Metadata-Version: 1.1
Name: ptolemaios
Version: 0.0.1
Summary: basic print func
Home-page: UNKNOWN
Author: Shabix Lampard
Author-email: charmzshab@gmail.com
License: MIT
Platform: UNKNOWN
Classifier: Development Status :: 5 - Production/Stable
Classifier: Intended Audience :: Education
Classifier: Operating System :: Microsoft :: Windows :: Windows 10
Classifier: License :: OSI Approved :: MIT License
Classifier: Programming Language :: Python :: 3
